.gitlab-ci.yml
CHANGES.rst
CONTRIBUTORS.rst
DEVELOP.rst
LICENSE.GPL
LICENSE.rst
MANIFEST.in
README.rst
constraints.txt
constraints_plone52.txt
constraints_plone60.txt
requirements.txt
requirements_plone52.txt
requirements_plone60.txt
setup.cfg
setup.py
tox.ini
docs/conf.py
docs/index.rst
src/collective/__init__.py
src/collective.redirect301.egg-info/PKG-INFO
src/collective.redirect301.egg-info/SOURCES.txt
src/collective.redirect301.egg-info/dependency_links.txt
src/collective.redirect301.egg-info/entry_points.txt
src/collective.redirect301.egg-info/namespace_packages.txt
src/collective.redirect301.egg-info/not-zip-safe
src/collective.redirect301.egg-info/requires.txt
src/collective.redirect301.egg-info/top_level.txt
src/collective/redirect301/__init__.py
src/collective/redirect301/configure.zcml
src/collective/redirect301/interfaces.py
src/collective/redirect301/permissions.zcml
src/collective/redirect301/setuphandlers.py
src/collective/redirect301/testing.py
src/collective/redirect301/browser/__init__.py
src/collective/redirect301/browser/browser.py
src/collective/redirect301/browser/configure.zcml
src/collective/redirect301/locales/README.rst
src/collective/redirect301/locales/__init__.py
src/collective/redirect301/locales/collective.redirect301.pot
src/collective/redirect301/locales/update.py
src/collective/redirect301/locales/update.sh
src/collective/redirect301/locales/en/LC_MESSAGES/collective.redirect301.po
src/collective/redirect301/profiles/default/browserlayer.xml
src/collective/redirect301/profiles/default/metadata.xml
src/collective/redirect301/profiles/uninstall/browserlayer.xml
src/collective/redirect301/tests/__init__.py
src/collective/redirect301/tests/test_setup.py